README.md
pytest_insubprocess.py
pytest_insubprocess-1.2.dist-info/METADATA
pytest_insubprocess-1.2.dist-info/WHEEL
pytest_insubprocess-1.2.dist-info/entry_points.txt
pytest_insubprocess-1.2.dist-info/RECORD
