Metadata-Version: 2.4
Name: pytest-insubprocess
Version: 1.2
Summary: A pytest plugin to execute test cases in a subprocess
Author-email: Pierre Chanial <pchanial@apc.in2p3.fr>
License-Expression: MIT
Keywords: pytest,subprocess,testing
Classifier: Development Status :: 4 - Beta
Classifier: Framework :: Pytest
Classifier: Programming Language :: Python :: 3
Classifier: Topic :: Software Development :: Testing
Requires-Python: >=3.7
Requires-Dist: pytest>=7.4
Requires-Dist: xmltodict
Provides-Extra: dev
Requires-Dist: pytest-rerunfailures; extra == 'dev'
